Project/final layout/dff.v
/*
 * Static D Flip-Flop (Positive Edge Triggered)
 * Author: Jai Srikar 2024102041
 */

module dff (
    input wire D,
    input wire CLK,
    output reg Q
);
    initial begin
        Q = 0;
    end

    always @(posedge CLK) begin
        Q <= D;
    end

endmodule

Project/testing/tb_trial.v
`timescale 1ns / 1ps
module dff_tb;
    reg D;
    reg CLK;
    wire Q;

    dff uut (
        .D(D), 
        .CLK(CLK), 
        .Q(Q)
    );

    always #0.5 CLK = ~CLK;

    initial begin
        CLK = 0;
        D = 0;
        $dumpfile("dff_tb.vcd");
        $dumpvars(0, dff_tb);

        #0.25 D = 1;  // Setup for first rising edge (at 1.0ns)
        #1.00 D = 0;  // Hold for first edge, setup for second
        #1.00 D = 1;  // High again
        #2.00 D = 0;
        
        #2.00 $finish;
    end

    initial begin
        $monitor("Time=%t | CLK=%b D=%b | Q=%b", $time, CLK, D, Q);
    end

endmodule

Project/testing/dff_tb.vcd
$date
	Wed Nov 19 11:58:58 2025
$end
$version
	Icarus Verilog
$end
$timescale
	1ps
$end
$scope module dff_tb $end
$var wire 1 ! Q $end
$var reg 1 " CLK $end
$var reg 1 # D $end
$scope module uut $end
$var wire 1 " CLK $end
$var wire 1 # D $end
$var reg 1 ! Q $end
$upscope $end
$upscope $end
$enddefinitions $end
$comment Show the parameter values. $end
$dumpall
$end
#0
$dumpvars
0#
0"
0!
$end
#250
1#
#500
1!
1"
#1000
0"
#1250
0#
#1500
0!
1"
#2000
0"
#2250
1#
#2500
1!
1"
#3000
0"
#3500
1"
#4000
0"
#4250
0#
#4500
0!
1"
