PROJECT V2/Verilog/integrated_cla5.v
`timescale 1ns/1ps

module cla5_pipelined (
    input  wire        clk,
    input  wire [4:0]  A_in,   
    input  wire [4:0]  B_in,    
    input  wire        Cin_in,  
    output wire [4:0]  S_out,   
    output wire        Cout_out  
);

    wire [4:0] A_reg;
    wire [4:0] B_reg;
    wire       Cin_reg;

    // Input Registers (Stage 1)
    genvar i;
    generate
        for (i=0; i<5; i=i+1) begin : gen_input_dffs_a
            dff_posedge dfa (.d(A_in[i]), .clk(clk), .q(A_reg[i]));
        end
        for (i=0; i<5; i=i+1) begin : gen_input_dffs_b
            dff_posedge dfb (.d(B_in[i]), .clk(clk), .q(B_reg[i]));
        end
    endgenerate

    dff_posedge dfc (.d(Cin_in), .clk(clk), .q(Cin_reg)); 

    // Combinational Logic (The Adder)
    wire [4:0] s_comb;
    wire       c_comb;
    
    cla5_manchester cla_inst (
        .A(A_reg),
        .B(B_reg),
        .Cin(Cin_reg),
        .S(s_comb),
        .Cout(c_comb)
    );

    // Output Registers (Stage 2)
    genvar j;
    generate
        for (j=0; j<5; j=j+1) begin : gen_output_dffs
            dff_posedge dfo (.d(s_comb[j]), .clk(clk), .q(S_out[j]));
        end
    endgenerate
    dff_posedge dfcout (.d(c_comb), .clk(clk), .q(Cout_out));

endmodule

// ============================================================
// MISSING MODULE 1: Positive Edge D Flip-Flop
// ============================================================
module dff_posedge (
    input wire d,
    input wire clk,
    output reg q
);
    always @(posedge clk) begin
        q <= d;
    end
endmodule

// ============================================================
// MISSING MODULE 2: 5-bit Manchester Adder (Logic Model)
// ============================================================
module cla5_manchester (
    input  wire [4:0] A,
    input  wire [4:0] B,
    input  wire       Cin,
    output wire [4:0] S,
    output wire       Cout
);
    // Carry Look-Ahead Logic
    wire [4:0] P, G;
    wire [5:0] C;

    // Propagate and Generate
    assign P = A ^ B; 
    assign G = A & B;

    // Carry Chain
    assign C[0] = Cin;
    assign C[1] = G[0] | (P[0] & C[0]);
    assign C[2] = G[1] | (P[1] & C[1]);
    assign C[3] = G[2] | (P[2] & C[2]);
    assign C[4] = G[3] | (P[3] & C[3]);
    assign C[5] = G[4] | (P[4] & C[4]);

    // Sum and Carry Out
    assign S = P ^ C[4:0];
    assign Cout = C[5];

endmodule

PROJECT V2/Verilog/tb_integrated.v
`timescale 1ns/1ps
module cla5_pipelined_tb;
    reg clk;
    reg [4:0] A_in;
    reg [4:0] B_in;
    reg       Cin_in;

    wire [4:0] S_out;
    wire       Cout_out;

    cla5_pipelined dut (
        .clk(clk),
        .A_in(A_in),
        .B_in(B_in),
        .Cin_in(Cin_in),
        .S_out(S_out),
        .Cout_out(Cout_out)
    );

    initial clk = 0;
    always #5 clk = ~clk;

    initial begin
        $dumpfile("cla5_pipelined_tb.vcd");
        $dumpvars(0, cla5_pipelined_tb);

        // initial test (0..40ns)
        A_in  = 5'b00011; B_in = 5'b00101; Cin_in = 1'b0;
        #40;

        // test 2 (40..80ns)
        A_in  = 5'b11111; B_in = 5'b00111; Cin_in = 1'b0;
        #40;

        // test 3 (80..120ns)
        A_in  = 5'b01010; B_in = 5'b01110; Cin_in = 1'b0;
        #40;

        // test 4 (120..160ns)
        A_in  = 5'b11100; B_in = 5'b11100; Cin_in = 1'b1;
        #40;

        $display("PIPELINED TB: finished at time %0t ns", $time);
        #20 $finish;
    end

    always @(posedge clk) begin
        #0; 
        $display("t=%0t ns : A_in=%b B_in=%b Cin=%b => S_out=%b Cout_out=%b", $time, A_in, B_in, Cin_in, S_out, Cout_out);
    end

    initial begin
        $display("Time(ns) | clk | A_in  B_in  Cin | S_out Cout_out");
        $monitor("%8t |  %b  | %b %b %b | %b %b", $time, clk, A_in, B_in, Cin_in, S_out, Cout_out);
    end

endmodule

PROJECT V2/Verilog/cla5_pipelined_tb.vcd
$date
	Thu Dec 04 09:40:12 2025
$end
$version
	Icarus Verilog
$end
$timescale
	1ps
$end
$scope module cla5_pipelined_tb $end
$var wire 5 ! S_out [4:0] $end
$var wire 1 " Cout_out $end
$var reg 5 # A_in [4:0] $end
$var reg 5 $ B_in [4:0] $end
$var reg 1 % Cin_in $end
$var reg 1 & clk $end
$scope module dut $end
$var wire 5 ' A_in [4:0] $end
$var wire 5 ( B_in [4:0] $end
$var wire 1 % Cin_in $end
$var wire 1 & clk $end
$var wire 5 ) s_comb [4:0] $end
$var wire 1 * c_comb $end
$var wire 5 + S_out [4:0] $end
$var wire 1 " Cout_out $end
$var wire 1 , Cin_reg $end
$var wire 5 - B_reg [4:0] $end
$var wire 5 . A_reg [4:0] $end
$scope begin gen_input_dffs_a[0] $end
$var parameter 2 / i $end
$scope module dfa $end
$var wire 1 & clk $end
$var wire 1 0 d $end
$var reg 1 1 q $end
$upscope $end
$upscope $end
$scope begin gen_input_dffs_a[1] $end
$var parameter 2 2 i $end
$scope module dfa $end
$var wire 1 & clk $end
$var wire 1 3 d $end
$var reg 1 4 q $end
$upscope $end
$upscope $end
$scope begin gen_input_dffs_a[2] $end
$var parameter 3 5 i $end
$scope module dfa $end
$var wire 1 & clk $end
$var wire 1 6 d $end
$var reg 1 7 q $end
$upscope $end
$upscope $end
$scope begin gen_input_dffs_a[3] $end
$var parameter 3 8 i $end
$scope module dfa $end
$var wire 1 & clk $end
$var wire 1 9 d $end
$var reg 1 : q $end
$upscope $end
$upscope $end
$scope begin gen_input_dffs_a[4] $end
$var parameter 4 ; i $end
$scope module dfa $end
$var wire 1 & clk $end
$var wire 1 < d $end
$var reg 1 = q $end
$upscope $end
$upscope $end
$scope begin gen_input_dffs_b[0] $end
$var parameter 2 > i $end
$scope module dfb $end
$var wire 1 & clk $end
$var wire 1 ? d $end
$var reg 1 @ q $end
$upscope $end
$upscope $end
$scope begin gen_input_dffs_b[1] $end
$var parameter 2 A i $end
$scope module dfb $end
$var wire 1 & clk $end
$var wire 1 B d $end
$var reg 1 C q $end
$upscope $end
$upscope $end
$scope begin gen_input_dffs_b[2] $end
$var parameter 3 D i $end
$scope module dfb $end
$var wire 1 & clk $end
$var wire 1 E d $end
$var reg 1 F q $end
$upscope $end
$upscope $end
$scope begin gen_input_dffs_b[3] $end
$var parameter 3 G i $end
$scope module dfb $end
$var wire 1 & clk $end
$var wire 1 H d $end
$var reg 1 I q $end
$upscope $end
$upscope $end
$scope begin gen_input_dffs_b[4] $end
$var parameter 4 J i $end
$scope module dfb $end
$var wire 1 & clk $end
$var wire 1 K d $end
$var reg 1 L q $end
$upscope $end
$upscope $end
$scope begin gen_output_dffs[0] $end
$var parameter 2 M j $end
$scope module dfo $end
$var wire 1 & clk $end
$var wire 1 N d $end
$var reg 1 O q $end
$upscope $end
$upscope $end
$scope begin gen_output_dffs[1] $end
$var parameter 2 P j $end
$scope module dfo $end
$var wire 1 & clk $end
$var wire 1 Q d $end
$var reg 1 R q $end
$upscope $end
$upscope $end
$scope begin gen_output_dffs[2] $end
$var parameter 3 S j $end
$scope module dfo $end
$var wire 1 & clk $end
$var wire 1 T d $end
$var reg 1 U q $end
$upscope $end
$upscope $end
$scope begin gen_output_dffs[3] $end
$var parameter 3 V j $end
$scope module dfo $end
$var wire 1 & clk $end
$var wire 1 W d $end
$var reg 1 X q $end
$upscope $end
$upscope $end
$scope begin gen_output_dffs[4] $end
$var parameter 4 Y j $end
$scope module dfo $end
$var wire 1 & clk $end
$var wire 1 Z d $end
$var reg 1 [ q $end
$upscope $end
$upscope $end
$scope module cla_inst $end
$var wire 5 \ A [4:0] $end
$var wire 5 ] B [4:0] $end
$var wire 5 ^ G [4:0] $end
$var wire 5 _ P [4:0] $end
$var wire 5 ` S [4:0] $end
$var wire 1 * Cout $end
$var wire 1 , Cin $end
$var wire 6 a C [5:0] $end
$upscope $end
$scope module dfc $end
$var wire 1 & clk $end
$var wire 1 % d $end
$var reg 1 , q $end
$upscope $end
$scope module dfcout $end
$var wire 1 & clk $end
$var wire 1 * d $end
$var reg 1 " q $end
$upscope $end
$upscope $end
$upscope $end
$enddefinitions $end
$comment Show the parameter values. $end
$dumpall
b100 Y
b11 V
b10 S
b1 P
b0 M
b100 J
b11 G
b10 D
b1 A
b0 >
b100 ;
b11 8
b10 5
b1 2
b0 /
$end
#0
$dumpvars
bx a
bx `
bx _
bx ^
bx ]
bx \
x[
xZ
xX
xW
xU
xT
xR
xQ
xO
xN
xL
0K
xI
0H
xF
1E
xC
0B
x@
1?
x=
0<
x:
09
x7
06
x4
13
x1
10
bx .
bx -
x,
bx +
x*
bx )
b101 (
b11 '
0&
0%
b101 $
b11 #
x"
bx !
$end
#5000
1W
0T
0Z
0Q
0*
0N
b1000 )
b1000 `
b110 _
b1 ^
11
14
07
0:
b11 .
b11 \
0=
1@
0C
1F
0I
b101 -
b101 ]
0L
b1110 a
0,
1&
#10000
0&
#15000
0"
0[
1X
0U
0R
b1000 !
b1000 +
0O
1&
#20000
0&
#25000
1&
#30000
0&
#35000
1&
#40000
1B
16
19
1<
0&
b111 $
b111 (
b11111 #
b11111 '
#45000
1*
b111110 a
0Z
0W
1T
1Q
b110 )
b110 `
b11000 _
b111 ^
17
1:
b11111 .
b11111 \
1=
b111 -
b111 ]
1C
1&
#50000
0&
#55000
1"
0X
1U
b110 !
b110 +
1R
1&
#60000
0&
#65000
1&
#70000
0&
#75000
1&
#80000
0?
1H
00
06
0<
0&
b1110 $
b1110 (
b1010 #
b1010 '
#85000
0Q
0*
1Z
1W
0T
b11100 a
b11000 )
b11000 `
b100 _
b1010 ^
01
07
b1010 .
b1010 \
0=
0@
b1110 -
b1110 ]
1I
1&
#90000
0&
#95000
0"
1[
1X
0U
b11000 !
b11000 +
0R
1&
#100000
0&
#105000
1&
#110000
0&
#115000
1&
#120000
0B
1K
03
16
1<
0&
1%
b11100 $
b11100 (
b11100 #
b11100 '
#125000
1*
0T
1N
b11001 )
b11001 `
b0 _
b11100 ^
04
17
b11100 .
b11100 \
1=
0C
b11100 -
b11100 ]
1L
b111001 a
1,
1&
#130000
0&
#135000
1"
b11001 !
b11001 +
1O
1&
